customner.py
customner-0.0.4.dist-info/METADATA
customner-0.0.4.dist-info/WHEEL
customner-0.0.4.dist-info/top_level.txt
customner-0.0.4.dist-info/RECORD
