Metadata-Version: 2.1
Name: customner
Version: 0.0.4
Summary: Custom Name Entity Recognition Data Preparation Library for Medical Dataset
Home-page: UNKNOWN
License: UNKNOWN
Platform: UNKNOWN
